{
	"audio": {
		"title": "Audio",
		"subtitle": "Accessibility",
		"letter": "A",
		"intro": {
			"p": "Lorem ipsum dolor sit amet, consectetur adipisicing elit. Eius incidunt, temporibus iure cupiditate hic modi voluptatem officia atque maiores, obcaecati eum aspernatur rem, consequuntur quos. In et, illum nisi voluptas facere cumque inventore, sed repellendus aliquid consectetur amet ex culpa vel ab! Magni nemo, eos quis accusantium labore mollitia placeat!",
			"img": {
				"src": "assets/img/dummy.png",
				"alt": "alt"
			}
		},
		"sections": [
			{
				"title": "Hiding Elements",
				"paragraphs": [
					{
						"li": "Most SR Obey <code class='language-css'>display:none</code> and <code class='language-css'>visibility:hidden</code> by not reading the text "
					},
					{
						"li": "The best way to hide text for users with vision but still let it be read out by screen readers is in css like this:",
						"pre": ".visuallyhidden {\n  border: 0;\n  clip: rect(0 0 0 0);\n  height: 1px;\n  margin: -1px;\n  overflow: hidden;\n  padding: 0;\n  position: absolute;\n  width: 1px;\n}",
						"preLang": "css"
					}
				],
				"subs": [
					{
						"title": "Section 1.1.",
						"paragraphs": [
							{
								"li": "hahaha"
							}
						]
					},
					{
						"title": "New Sub",
						"paragraphs": [
							{
								"li": "hahaha"
							}
						]
					}
				]
			},
			{
				"title": "Section2",
				"paragraphs": [
					{
						"p": "dolor sit"
					},
					{
						"img": "only img"
					}
				],
				"subs": [
					{
						"title": "test2"
					}
				]
			}
		]
	},
	"cognitive": {
		"title": "Cognitive",
		"subtitle": "Accessibility",
		"letter": "C",
		"intro": {
			"p": "Lorem ipsum dolor sit amet, consectetur adipisicing elit. Eius incidunt, temporibus iure cupiditate hic modi voluptatem officia atque maiores, obcaecati eum aspernatur rem, consequuntur quos. In et, illum nisi voluptas facere cumque inventore, sed repellendus aliquid consectetur amet ex culpa vel ab! Magni nemo, eos quis accusantium labore mollitia placeat!",
			"img": {
				"src": "assets/img/dummy.png",
				"alt": "alt"
			}
		},
		"sections": [
			{
				"title": "Hiding Elements",
				"paragraphs": [
					{
						"li": "Most SR Obey <code class='language-css'>display:none</code> and <code class='language-css'>visibility:hidden</code> by not reading the text "
					},
					{
						"li": "The best way to hide text for users with vision but still let it be read out by screen readers is in css like this:",
						"pre": ".visuallyhidden {\n  border: 0;\n  clip: rect(0 0 0 0);\n  height: 1px;\n  margin: -1px;\n  overflow: hidden;\n  padding: 0;\n  position: absolute;\n  width: 1px;\n}",
						"preLang": "css"
					}
				],
				"subs": [
					{
						"title": "Section 1.1.",
						"paragraphs": [
							{
								"li": "hahaha"
							}
						]
					},
					{
						"title": "New Sub",
						"paragraphs": [
							{
								"li": "hahaha"
							}
						]
					}
				]
			},
			{
				"title": "Section2",
				"paragraphs": [
					{
						"p": "dolor sit"
					},
					{
						"img": "only img"
					}
				],
				"subs": [
					{
						"title": "test2"
					}
				]
			}
		]
	},
	"home": {
		"letters": [
			"A",
			"c",
			"c",
			"e",
			"s",
			"s",
			"i",
			"b",
			"i",
			"l",
			"i",
			"t",
			"y",
			"i",
			"s"
		],
		"title": "Accessibility",
		"subtitle": "for everyone",
		"nav": {
			"mainmenu": "Main menu",
			"options": [
				{
					"url": "visual.html",
					"title": "V",
					"description": "visual",
					"sr": "accessibility"
				},
				{
					"url": "audio.html",
					"title": "A",
					"description": "audio",
					"sr": "accessibility"
				},
				{
					"url": "physical.html",
					"title": "P",
					"description": "physical",
					"sr": "accessibility"
				},
				{
					"url": "cognitive.html",
					"title": "C",
					"description": "Cognitive",
					"sr": "accessibility"
				}
			]
		}
	},
	"physical": {
		"title": "Physical",
		"subtitle": "Accessibility",
		"letter": "P",
		"intro": {
			"p": "Lorem ipsum dolor sit amet, consectetur adipisicing elit. Eius incidunt, temporibus iure cupiditate hic modi voluptatem officia atque maiores, obcaecati eum aspernatur rem, consequuntur quos. In et, illum nisi voluptas facere cumque inventore, sed repellendus aliquid consectetur amet ex culpa vel ab! Magni nemo, eos quis accusantium labore mollitia placeat!",
			"img": {
				"src": "assets/img/dummy.png",
				"alt": "alt"
			}
		},
		"sections": [
			{
				"title": "Hiding Elements",
				"paragraphs": [
					{
						"li": "Most SR Obey <code class='language-css'>display:none</code> and <code class='language-css'>visibility:hidden</code> by not reading the text "
					},
					{
						"li": "The best way to hide text for users with vision but still let it be read out by screen readers is in css like this:",
						"pre": ".visuallyhidden {\n  border: 0;\n  clip: rect(0 0 0 0);\n  height: 1px;\n  margin: -1px;\n  overflow: hidden;\n  padding: 0;\n  position: absolute;\n  width: 1px;\n}",
						"preLang": "css"
					}
				],
				"subs": [
					{
						"title": "Section 1.1.",
						"paragraphs": [
							{
								"li": "hahaha"
							}
						]
					},
					{
						"title": "New Sub",
						"paragraphs": [
							{
								"li": "hahaha"
							}
						]
					}
				]
			},
			{
				"title": "Section2",
				"paragraphs": [
					{
						"p": "dolor sit"
					},
					{
						"img": "only img"
					}
				],
				"subs": [
					{
						"title": "test2"
					}
				]
			}
		]
	},
	"shared": {
		"toc": {
			"title": "Table of contents for",
			"V": 1,
			"A": 2,
			"P": 3,
			"C": 4
		},
		"nav": {
			"title": "Main menu",
			"selected": "current:",
			"options": [
				{
					"url": "visual.html",
					"title": "V",
					"description": "visual",
					"sr": "accessibility"
				},
				{
					"url": "audio.html",
					"title": "A",
					"description": "audio",
					"sr": "accessibility"
				},
				{
					"url": "physical.html",
					"title": "P",
					"description": "physical",
					"sr": "accessibility"
				},
				{
					"url": "cognitive.html",
					"title": "C",
					"description": "Cognitive",
					"sr": "accessibility"
				}
			]
		},
		"sections": {
			"output": "Visual output",
			"audio": "Screen reader",
			"example": "Code example",
			"skip": "skip code example to next item"
		}
	},
	"visual": {
		"title": "Visual",
		"subtitle": "Accessibility",
		"letter": "V",
		"intro": {
			"p": "Speaking of web-accessibility, the visually impaired have the most painpoints. <a href=\"http://www.euroblind.org/resources/information/\">According to the EBU</a> more than 4% of the european population is blind or partially sighted. They use screen reader. A screen reader is a tool that reads content aloud. There are different types of screen readers, the most popular Screen Readers are JAWS and Zoom Text:",
			"img": {
				"src": "assets/img/sr-stats.png",
				"alt": "Chart of primary screen reader usage showing decreases in JAWS, NVDA, VoiceOver, SA and significant increases in ZoomText and Window-Eyes.",
				"caption": "Chart based on Data from <a href=\"http://webaim.org/projects/screenreadersurvey6/#primary\">webaim.org</a> a textual description can be found there."
			},
			"ul": [
				"All concepts introduced on this page were tested with VoiceOver and JAWS in June 2016."
			]
		},
		"sections": [
			{
				"title": "Basic Facts",
				"paragraphs": [
					{
						"anchor": "what screen reader can do",
						"li": "Screen reader can read text, and interpret special attributes written in HTML, most modern screen reader can also list common items as all headers, links, forms and tables."
					},
					{
						"anchor": "screen reader painpoints",
						"li": "The usual painpoints are a bad page strukture, images, svg, graphs, videos, forms, tables, repetitive elements, visual features, popups."
					},
					{
						"anchor": "screen reader javascript",
						"li": "Screen readers have <a href=\"http://webaim.org/projects/screenreadersurvey4/#javascript\">no problems using javascript</a>."
					}
				]
			},
			{
				"title": "Hiding Elements",
				"paragraphs": [
					{
						"anchor": "screen reader display none",
						"li": "Almost all screen reader obey <code class='language-css'>display:none</code> and <code class='language-css'>visibility:hidden</code> by ignoring the element."
					},
					{
						"anchor": "screen reader visually hidden",
						"li": "To have elements visually hidden but still accessible for screen readers the <a href=\"https://www.w3.org/WAI/tutorials/forms/labels/#note-on-hiding-elements\">W3C suggests</a> this css method:",
						"pre": ".visuallyhidden {\n  border: 0;\n  clip: rect(0 0 0 0);\n  height: 1px;\n  margin: -1px;\n  overflow: hidden;\n  padding: 0;\n  position: absolute;\n  width: 1px;\n}",
						"preLang": "css"
					},
					{
						"anchor": "screen reader aria hidden",
						"li": "Of course you can also do the contrary. Hide text for screen readers but show it visually by using <code class='language-markup'>aria-hidden=\"true\"</code>. The support for aria-hidden is <a href=\"http://www.html5accessibility.com/tests/hidden2013.html\">brilliant</a>."
					},
					{
						"anchor": "screen reader hiding example",
						"li": "This is how a screenreader would typically interpret the different hiding methods:",
						"example": {
							"pre": "I love\n <span style=\"display:none;\">bees</span>\n <span class=\"visuallyhidden\">cats</span>\n <span hidden>and</span>\n <span aria-hidden=\"true\">you</span>",
							"preLang": "markup",
							"play": "Listen ♫",
							"audio": "I love cats"
						}
					}
				],
				"subs": [
					{
						"title": "Section 1.1.",
						"paragraphs": [
							{
								"li": "hahaha"
							}
						]
					},
					{
						"title": "New Sub",
						"paragraphs": [
							{
								"li": "hahaha"
							}
						]
					}
				]
			},
			{
				"title": "Section2",
				"paragraphs": [
					{
						"p": "dolor sit"
					},
					{
						"img": "only img"
					}
				],
				"subs": [
					{
						"title": "test2"
					}
				]
			}
		]
	},
	"welcome": {
		"title": "0. Why should you care?",
		"screenReader": "Hello dear ScreenReader user, you are the best :)",
		"skip": "skip intro",
		"writings": [
			{
				"screenReader": "When you build a website or a webapp, you want it to be successfull. Right?",
				"texts": [
					"When you build a",
					"website,",
					"you want it to be",
					"successfull.",
					"Right?"
				],
				"button": "YES",
				"img": "assets/img/wobble_success.gif"
			},
			{
				"screenReader": "You want everyone to use it. Right?",
				"texts": [
					"You want",
					"everyone",
					"to use it. Right?"
				],
				"img": "assets/img/wobble_world.gif"
			},
			{
				"screenReader": "Then, why would you leave out eleven percent of the population?",
				"texts": [
					"Then, why would you leave out",
					"around 11%",
					"of the population?"
				],
				"img": "assets/img/wobble_heartbreak.gif"
			},
			{
				"screenReader": "Imagine increasing sales by eleven percent, while doing good. Neat right?",
				"texts": [
					"Imagine your sales",
					"increasing",
					"by 11% while doing",
					"good..."
				],
				"img": "assets/img/wobble_money.gif"
			},
			{
				"screenReader": "so...",
				"texts": [
					".......",
					"So..."
				]
			},
			{
				"screenReader": "Open up your websites for the physically impaired. Make them accessible!",
				"texts": [
					"Open up your website.",
					"Make it",
					"accessible for",
					"everyone!"
				],
				"img": "assets/img/wobble_luv.gif"
			},
			{
				"screenReader": "It is not difficult, nor will it cost a fortune. You have no excuse.",
				"texts": [
					"It’s not difficult & it will",
					"not cost",
					"a fortune. You have",
					"no excuse."
				],
				"img": "assets/img/wobble_excuse.gif"
			},
			{
				"screenReader": "Accessibility is like opening your door to everyone.",
				"texts": [
					"Accessibility is just like",
					"opening",
					"your door."
				],
				"img": "assets/img/wobble_door-0.gif",
				"last": "learn accessibility"
			}
		]
	}
}